odoo_sh_gitlab_ci/__init__.py
odoo_sh_gitlab_ci/deploy.py
odoo_sh_gitlab_ci-1.0.18.dist-info/METADATA
odoo_sh_gitlab_ci-1.0.18.dist-info/WHEEL
odoo_sh_gitlab_ci-1.0.18.dist-info/entry_points.txt
odoo_sh_gitlab_ci-1.0.18.dist-info/top_level.txt
odoo_sh_gitlab_ci-1.0.18.dist-info/RECORD
