Metadata-Version: 2.4
Name: odoo-sh-gitlab-ci
Version: 1.0.18
Summary: Simplify and automate Odoo.sh deployment using GitLab and GitHub.
Author-email: Jarsa <info@jarsa.com>
License-Expression: AGPL-3.0-only
Classifier: Programming Language :: Python :: 3
Classifier: Programming Language :: Python :: 3 :: Only
Classifier: Operating System :: OS Independent
Requires-Python: >=3.9
